verifycode/__init__.py
verifycode/generator.py
verifycode/test_generator.py
verifycode-0.2.2.dist-info/LICENSE
verifycode-0.2.2.dist-info/METADATA
verifycode-0.2.2.dist-info/WHEEL
verifycode-0.2.2.dist-info/top_level.txt
verifycode-0.2.2.dist-info/RECORD
