Metadata-Version: 2.1
Name: verifycode
Version: 0.2.2
Summary: a library for generate verificatio code png
Home-page: https://github.com/yeqown/verification_code
Author: Yeqown
Author-email: yeqown@gmail.com
License: MIT License
Keywords: verificationcode
Platform: OSX
Platform: win
Requires-Dist: pillow
